pytest-item-dict/examples/conftest.py
pytest-item-dict/examples/py.typed
pytest-item-dict/examples/suites/it/linux/test_linux.py
pytest-item-dict/examples/suites/it/windows/test_windows.py
pytest-item-dict/examples/suites/vt/linux/test_v_linux.py
pytest-item-dict/examples/suites/vt/linux/test_v_posix.py
pytest-item-dict/examples/suites/vt/windows/test_v_windows.py
pytest-item-dict/src/pytest_item_dict/__init__.py
pytest-item-dict/src/pytest_item_dict/collect_dict.py
pytest-item-dict/src/pytest_item_dict/hooks.py
pytest-item-dict/src/pytest_item_dict/item_dict_enums.py
pytest-item-dict/src/pytest_item_dict/plugin.py
pytest-item-dict/src/pytest_item_dict/py.typed
pytest-item-dict/src/pytest_item_dict/test_dict.py
pytest-item-dict/src/pytest_item_dict/version.py
pytest-item-dict/test_dev/conftest.py
pytest-item-dict/test_dev/py.typed
pytest-item-dict/test_dev/suites/it/linux/test_linux.py
pytest-item-dict/test_dev/suites/it/windows/test_windows.py
pytest-item-dict/test_dev/suites/vt/linux/test_v_linux.py
pytest-item-dict/test_dev/suites/vt/linux/test_v_posix.py
pytest-item-dict/test_dev/suites/vt/windows/test_v_windows.py
pytest-item-dict/tests/conftest.py
pytest-item-dict/tests/py.typed
pytest-item-dict/tests/test_item_dict.py
pytest-item-dict/utils/create_docs.py
pytest_item_dict/__init__.py
pytest_item_dict/collect_dict.py
pytest_item_dict/hooks.py
pytest_item_dict/item_dict_enums.py
pytest_item_dict/plugin.py
pytest_item_dict/py.typed
pytest_item_dict/test_dict.py
pytest_item_dict/version.py
pytest_item_dict-1.1.2.dist-info/LICENSE
pytest_item_dict-1.1.2.dist-info/METADATA
pytest_item_dict-1.1.2.dist-info/WHEEL
pytest_item_dict-1.1.2.dist-info/entry_points.txt
pytest_item_dict-1.1.2.dist-info/top_level.txt
pytest_item_dict-1.1.2.dist-info/RECORD
