Metadata-Version: 2.1
Name: pytest-item-dict
Version: 1.1.2
Summary: Get a hierarchical dict of session.items
Author-email: Adam Nogowski <anogowski@live.com>
Maintainer-email: Adam Nogowski <anogowski@live.com>
License: Dual License: All software and documentation is distributed under "BSD 3-Clause License" AND "Mozilla Public License Version 2.0"
Project-URL: Repository, https://github.com/anogowski/pytest-item-dict
Keywords: pytest,items,dict,session.items,session,hierarchical,hierarchy,tree
Classifier: Framework :: Pytest
Classifier: Development Status :: 4 - Beta
Classifier: Intended Audience :: Developers
Classifier: Operating System :: OS Independent
Classifier: Programming Language :: Python
Classifier: Programming Language :: Python :: 3.11
Classifier: Programming Language :: Python :: 3.12
Classifier: Programming Language :: Python :: 3.13
Classifier: Programming Language :: Python :: 3 :: Only
Classifier: Programming Language :: Python :: Implementation :: CPython
Classifier: Programming Language :: Python :: Implementation :: PyPy
Classifier: License :: OSI Approved :: BSD License
Classifier: License :: OSI Approved :: Mozilla Public License 2.0 (MPL 2.0)
Classifier: Topic :: Software Development :: Quality Assurance
Classifier: Topic :: Software Development :: Testing
Classifier: Topic :: Utilities
Requires-Python: >=3.11
License-File: LICENSE
Requires-Dist: pytest>=8.3.0
